apirun/__init__.py
apirun/cli.py
apirun/cli_help_i18n.py
apirun/core/__init__.py
apirun/core/models.py
apirun/core/retry.py
apirun/core/template_functions.py
apirun/core/variable_manager.py
apirun/data_driven/__init__.py
apirun/data_driven/data_source.py
apirun/data_driven/iterator.py
apirun/executor/__init__.py
apirun/executor/api_executor.py
apirun/executor/concurrent_executor.py
apirun/executor/database_executor.py
apirun/executor/loop_executor.py
apirun/executor/script_executor.py
apirun/executor/step_executor.py
apirun/executor/test_case_executor.py
apirun/executor/wait_executor.py
apirun/extractor/__init__.py
apirun/extractor/cookie_extractor.py
apirun/extractor/extractor_factory.py
apirun/extractor/header_extractor.py
apirun/extractor/jsonpath_extractor.py
apirun/extractor/regex_extractor.py
apirun/mock/__init__.py
apirun/mock/models.py
apirun/mock/server.py
apirun/parser/__init__.py
apirun/parser/v2_yaml_parser.py
apirun/result/__init__.py
apirun/result/allure_exporter.py
apirun/result/html_exporter.py
apirun/result/json_exporter.py
apirun/result/junit_exporter.py
apirun/utils/__init__.py
apirun/utils/enhanced_jsonpath.py
apirun/utils/error_utils.py
apirun/utils/hooks.py
apirun/utils/json_optimized.py
apirun/utils/performance.py
apirun/utils/template.py
apirun/validation/__init__.py
apirun/validation/comparators.py
apirun/validation/engine.py
apirun/websocket/__init__.py
apirun/websocket/broadcaster.py
apirun/websocket/events.py
apirun/websocket/notifier.py
apirun/websocket/progress.py
apirun/websocket/server.py
docs/API-Engine输入协议规范.md
docs/API-Engine输出协议规范.md
docs/bugfixes_summary.md
sisyphus_api_engine-1.0.3.dist-info/licenses/LICENSE
sisyphus_api_engine-1.0.3.dist-info/METADATA
sisyphus_api_engine-1.0.3.dist-info/WHEEL
sisyphus_api_engine-1.0.3.dist-info/entry_points.txt
sisyphus_api_engine-1.0.3.dist-info/top_level.txt
sisyphus_api_engine-1.0.3.dist-info/RECORD
