Metadata-Version: 2.4
Name: Sisyphus-api-engine
Version: 1.0.3
Summary: Enterprise-grade API automation testing engine with YAML-based declarative syntax, supporting complex testing scenarios including HTTP/HTTPS, database operations, data-driven testing, concurrent execution, and real-time WebSocket reporting.
Author-email: koco-co <kopohub@gmail.com>
Maintainer-email: koco-co <kopohub@gmail.com>
License: MIT
Project-URL: Homepage, https://github.com/koco-co/Sisyphus-api-engine
Project-URL: Documentation, https://github.com/koco-co/Sisyphus-api-engine/blob/main/README.md
Project-URL: Repository, https://github.com/koco-co/Sisyphus-api-engine.git
Project-URL: Bug Tracker, https://github.com/koco-co/Sisyphus-api-engine/issues
Project-URL: Changelog, https://github.com/koco-co/Sisyphus-api-engine/blob/main/README.md#-更新日志
Keywords: api,testing,automation,yaml,json,mock,concurrent,allure,websocket,ddt,data-driven
Classifier: Development Status :: 5 - Production/Stable
Classifier: Intended Audience :: Developers
Classifier: Topic :: Software Development :: Quality Assurance
Classifier: Topic :: Software Development :: Testing
Classifier: Topic :: Software Development :: Testing :: Unit
Classifier: Topic :: Software Development :: Testing :: Acceptance
Classifier: License :: OSI Approved :: MIT License
Classifier: Programming Language :: Python :: 3
Classifier: Programming Language :: Python :: 3.8
Classifier: Programming Language :: Python :: 3.9
Classifier: Programming Language :: Python :: 3.10
Classifier: Programming Language :: Python :: 3.11
Classifier: Programming Language :: Python :: 3.12
Classifier: Operating System :: OS Independent
Classifier: Natural Language :: English
Classifier: Natural Language :: Chinese (Simplified)
Requires-Python: >=3.8
License-File: LICENSE
Requires-Dist: Jinja2>=3.0.0
Requires-Dist: jsonpath-ng>=1.6.0
Requires-Dist: PyYAML>=6.0
Requires-Dist: pyyaml-include>=1.3
Requires-Dist: requests>=2.28.0
Requires-Dist: httpx>=0.24.0
Requires-Dist: PyMySQL>=1.0.0
Requires-Dist: SQLAlchemy>=2.0.0
Requires-Dist: typing-extensions>=4.5.0
Requires-Dist: python-dateutil>=2.8.0
Requires-Dist: Flask>=3.0.0
Requires-Dist: websockets>=12.0
Provides-Extra: dev
Requires-Dist: pytest>=7.0.0; extra == "dev"
Requires-Dist: pytest-cov>=4.0.0; extra == "dev"
Requires-Dist: pytest-asyncio>=0.21.0; extra == "dev"
Requires-Dist: black>=23.0.0; extra == "dev"
Requires-Dist: isort>=5.12.0; extra == "dev"
Requires-Dist: flake8>=6.0.0; extra == "dev"
Requires-Dist: mypy>=1.0.0; extra == "dev"
Requires-Dist: pylint>=2.17.0; extra == "dev"
Provides-Extra: docs
Requires-Dist: sphinx>=5.0.0; extra == "docs"
Requires-Dist: sphinx-rtd-theme>=1.2.0; extra == "docs"
Requires-Dist: myst-parser>=1.0.0; extra == "docs"
Provides-Extra: all
Requires-Dist: Sisyphus-api-engine[dev,docs]; extra == "all"
Dynamic: license-file
